steamdt_mcp/__init__.py
steamdt_mcp/server.py
iflow_mcp_kir4kami_mcp_steamdt-0.1.0.dist-info/METADATA
iflow_mcp_kir4kami_mcp_steamdt-0.1.0.dist-info/WHEEL
iflow_mcp_kir4kami_mcp_steamdt-0.1.0.dist-info/entry_points.txt
iflow_mcp_kir4kami_mcp_steamdt-0.1.0.dist-info/top_level.txt
iflow_mcp_kir4kami_mcp_steamdt-0.1.0.dist-info/RECORD
