Metadata-Version: 2.4
Name: iflow-mcp_kir4kami_mcp-steamdt
Version: 0.1.0
Summary: SteamDT MCP server for querying CS2 item prices and market data
Author-email: Kir4kami <kir4kami@users.noreply.github.com>
License: MIT
Project-URL: Homepage, https://github.com/Kir4kami/mcp-steamdt
Project-URL: Repository, https://github.com/Kir4kami/mcp-steamdt
Requires-Python: >=3.10
Requires-Dist: httpx>=0.27.0
Requires-Dist: mcp>=1.0.0
Requires-Dist: python-dotenv>=1.0.0
